{
  "orgNav": {
    "links": [
      {
        "text": "Board of Trustees",
        "href": "http://www.google.com",
        "class": "ama__link ama__link--purple"
      },
      {
        "text": "House of Delegates",
        "href": "http://www.yahoo.com",
        "class": "ama__link ama__link--purple"
      },
      {
        "text": "Councils & Committees",
        "href": "http://www.yahoo.com",
        "class": "ama__link ama__link--purple"
      },
      {
        "text": "Member Groups",
        "href": "http://www.yahoo.com",
        "class": "ama__link ama__link--purple"
      }
    ]
  }
}
