{
  "pageGrouping": {
    "title": "COVID-19 Resource Center",
    "image": "https://via.placeholder.com/142x80",
    "updateSection": {
      "title": "Featured Updates",
      "updates": [
        {
          "title": "Clinical Information",
          "url": "#"
        },
        {
          "title": "AMA Guides and Resources",
          "url": "#"
        },
        {
          "title": "Advocacy",
          "url": "#"
        },
        {
          "title": "Medical Ethics",
          "url": "#"
        }
      ]
    }
  }
}
